[
    {
        "id": "1",
        "gender": "Male",
        "name": "John Doe",
        "contact": "+1234567890",
        "address": "123 Main St, City",
        "photoURL": "https://example.com/photos/1.jpg"
    },
    {
        "id": "2",
        "gender": "Female",
        "name": "Jane Smith",
        "contact": "+9876543210",
        "address": "456 Elm St, Town",
        "photoURL": "https://example.com/photos/2.jpg"
    },
    {
        "id": "3",
        "gender": "Male",
        "name": "Alex Johnson",
        "contact": "+5555555555",
        "address": "789 Oak Ave, Village",
        "photoURL": "https://example.com/photos/3.jpg"
    },
    {
        "id": "4",
        "gender": "Female",
        "name": "Emily Wilson",
        "contact": "+4444444444",
        "address": "567 Pine St, Town",
        "photoURL": "https://example.com/photos/4.jpg"
    },
    {
        "id": "5",
        "gender": "Male",
        "name": "Michael Brown",
        "contact": "+2222222222",
        "address": "890 Maple Ave, City",
        "photoURL": "https://example.com/photos/5.jpg"
    },
    {
        "id": "6",
        "gender": "Female",
        "name": "Sarah Davis",
        "contact": "+6666666666",
        "address": "432 Oak St, Village",
        "photoURL": "https://example.com/photos/6.jpg"
    },
    {
        "id": "7",
        "gender": "Male",
        "name": "Christopher Lee",
        "contact": "+7777777777",
        "address": "654 Elm Ave, Town",
        "photoURL": "https://example.com/photos/7.jpg"
    },
    {
        "id": "8",
        "gender": "Female",
        "name": "Olivia Thompson",
        "contact": "+9999999999",
        "address": "987 Main St, City",
        "photoURL": "https://example.com/photos/8.jpg"
    },
    {
        "id": "9",
        "gender": "Male",
        "name": "Daniel Garcia",
        "contact": "+8888888888",
        "address": "321 Pine Ave, Village",
        "photoURL": "https://example.com/photos/9.jpg"
    },
    {
        "id": "10",
        "gender": "Female",
        "name": "Sophia Hernandez",
        "contact": "+1111111111",
        "address": "654 Maple St, Town",
        "photoURL": "https://example.com/photos/10.jpg"
    },
    {
        "id": "11",
        "gender": "Male",
        "name": "Matthew Wilson",
        "contact": "+2222222222",
        "address": "876 Oak Ave, City",
        "photoURL": "https://example.com/photos/11.jpg"
    },
    {
        "id": "12",
        "gender": "Female",
        "name": "Ava Lopez",
        "contact": "+3333333333",
        "address": "987 Elm St, Village",
        "photoURL": "https://example.com/photos/12.jpg"
    },
    {
        "id": "13",
        "gender": "Male",
        "name": "Andrew Clark",
        "contact": "+4444444444",
        "address": "543 Pine Ave, Town",
        "photoURL": "https://example.com/photos/13.jpg"
    },
    {
        "id": "14",
        "gender": "Female",
        "name": "Isabella Rodriguez",
        "contact": "+5555555555",
        "address": "210 Main St, City",
        "photoURL": "https://example.com/photos/14.jpg"
    },
    {
        "id": "15",
        "gender": "Male",
        "name": "Ethan Green",
        "contact": "+6666666666",
        "address": "876 Elm St, Village",
        "photoURL": "https://example.com/photos/15.jpg"
    },
    {
        "id": "16",
        "gender": "Female",
        "name": "Mia Martinez",
        "contact": "+7777777777",
        "address": "543 Oak Ave, Town",
        "photoURL": "https://example.com/photos/16.jpg"
    },
    {
        "id": "17",
        "gender": "Male",
        "name": "James Taylor",
        "contact": "+8888888888",
        "address": "210 Pine St, City",
        "photoURL": "https://example.com/photos/17.jpg"
    },
    {
        "id": "18",
        "gender": "Female",
        "name": "Charlotte Brown",
        "contact": "+9999999999",
        "address": "876 Maple Ave, Village",
        "photoURL": "https://example.com/photos/18.jpg"
    },
    {
        "id": "19",
        "gender": "Male",
        "name": "Benjamin Johnson",
        "contact": "+1111111111",
        "address": "543 Oak St, Town",
        "photoURL": "https://example.com/photos/19.jpg"
    },
    {
        "id": "20",
        "gender": "Female",
        "name": "Harper Smith",
        "contact": "+2222222222",
        "address": "210 Main Ave, City",
        "photoURL": "https://example.com/photos/20.jpg"
    },
    {
        "id": "21",
        "gender": "Male",
        "name": "Logan Wilson",
        "contact": "+3333333333",
        "address": "876 Elm St, Village",
        "photoURL": "https://example.com/photos/21.jpg"
    },
    {
        "id": "22",
        "gender": "Female",
        "name": "Amelia Davis",
        "contact": "+4444444444",
        "address": "543 Oak Ave, Town",
        "photoURL": "https://example.com/photos/22.jpg"
    },
    {
        "id": "23",
        "gender": "Male",
        "name": "Lucas Anderson",
        "contact": "+5555555555",
        "address": "210 Pine St, City",
        "photoURL": "https://example.com/photos/23.jpg"
    },
    {
        "id": "24",
        "gender": "Female",
        "name": "Grace Thomas",
        "contact": "+6666666666",
        "address": "876 Maple Ave, Village",
        "photoURL": "https://example.com/photos/24.jpg"
    },
    {
        "id": "25",
        "gender": "Male",
        "name": "Henry Taylor",
        "contact": "+7777777777",
        "address": "543 Oak St, Town",
        "photoURL": "https://example.com/photos/25.jpg"
    },
    {
        "id": "26",
        "gender": "Female",
        "name": "Luna Martinez",
        "contact": "+8888888888",
        "address": "210 Main Ave, City",
        "photoURL": "https://example.com/photos/26.jpg"
    },
    {
        "id": "27",
        "gender": "Male",
        "name": "Liam Brown",
        "contact": "+9999999999",
        "address": "876 Elm St, Village",
        "photoURL": "https://example.com/photos/27.jpg"
    },
    {
        "id": "28",
        "gender": "Female",
        "name": "Victoria Johnson",
        "contact": "+1111111111",
        "address": "543 Oak Ave, Town",
        "photoURL": "https://example.com/photos/28.jpg"
    },
    {
        "id": "29",
        "gender": "Male",
        "name": "Sebastian Smith",
        "contact": "+2222222222",
        "address": "210 Pine St, City",
        "photoURL": "https://example.com/photos/29.jpg"
    },
    {
        "id": "30",
        "gender": "Female",
        "name": "Evelyn Wilson",
        "contact": "+3333333333",
        "address": "876 Maple Ave, Village",
        "photoURL": "https://example.com/photos/30.jpg"
    },
    {
        "id": "31",
        "gender": "Male",
        "name": "Jackson Davis",
        "contact": "+4444444444",
        "address": "543 Oak St, Town",
        "photoURL": "https://example.com/photos/31.jpg"
    },
    {
        "id": "32",
        "gender": "Female",
        "name": "Penelope Anderson",
        "contact": "+5555555555",
        "address": "210 Pine St, City",
        "photoURL": "https://example.com/photos/32.jpg"
    },
    {
        "id": "33",
        "gender": "Male",
        "name": "David Clark",
        "contact": "+6666666666",
        "address": "876 Elm St, Village",
        "photoURL": "https://example.com/photos/33.jpg"
    },
    {
        "id": "34",
        "gender": "Female",
        "name": "Sofia Thomas",
        "contact": "+7777777777",
        "address": "543 Oak Ave, Town",
        "photoURL": "https://example.com/photos/34.jpg"
    },
    {
        "id": "35",
        "gender": "Male",
        "name": "Aiden Rodriguez",
        "contact": "+8888888888",
        "address": "210 Pine St, City",
        "photoURL": "https://example.com/photos/35.jpg"
    },
    {
        "id": "36",
        "gender": "Female",
        "name": "Avery Green",
        "contact": "+9999999999",
        "address": "876 Maple Ave, Village",
        "photoURL": "https://example.com/photos/36.jpg"
    },
    {
        "id": "37",
        "gender": "Male",
        "name": "Carter Taylor",
        "contact": "+1111111111",
        "address": "543 Oak St, Town",
        "photoURL": "https://example.com/photos/37.jpg"
    },
    {
        "id": "38",
        "gender": "Female",
        "name": "Scarlett Smith",
        "contact": "+2222222222",
        "address": "210 Pine St, City",
        "photoURL": "https://example.com/photos/38.jpg"
    },
    {
        "id": "39",
        "gender": "Male",
        "name": "Wyatt Wilson",
        "contact": "+3333333333",
        "address": "876 Elm St, Village",
        "photoURL": "https://example.com/photos/39.jpg"
    },
    {
        "id": "40",
        "gender": "Female",
        "name": "Hannah Davis",
        "contact": "+4444444444",
        "address": "543 Oak Ave, Town",
        "photoURL": "https://example.com/photos/40.jpg"
    },
    {
        "id": "41",
        "gender": "Male",
        "name": "Owen Anderson",
        "contact": "+5555555555",
        "address": "210 Pine St, City",
        "photoURL": "https://example.com/photos/41.jpg"
    },
    {
        "id": "42",
        "gender": "Female",
        "name": "Abigail Clark",
        "contact": "+6666666666",
        "address": "876 Maple Ave, Village",
        "photoURL": "https://example.com/photos/42.jpg"
    },
    {
        "id": "43",
        "gender": "Male",
        "name": "Grayson Johnson",
        "contact": "+7777777777",
        "address": "543 Oak St, Town",
        "photoURL": "https://example.com/photos/43.jpg"
    },
    {
        "id": "44",
        "gender": "Female",
        "name": "Zoe Brown",
        "contact": "+8888888888",
        "address": "210 Pine St, City",
        "photoURL": "https://example.com/photos/44.jpg"
    },
    {
        "id": "45",
        "gender": "Male",
        "name": "Levi Taylor",
        "contact": "+9999999999",
        "address": "876 Elm St, Village",
        "photoURL": "https://example.com/photos/45.jpg"
    },
    {
        "id": "46",
        "gender": "Female",
        "name": "Nora Smith",
        "contact": "+1111111111",
        "address": "543 Oak Ave, Town",
        "photoURL": "https://example.com/photos/46.jpg"
    },
    {
        "id": "47",
        "gender": "Male",
        "name": "Henry Davis",
        "contact": "+2222222222",
        "address": "210 Pine St, City",
        "photoURL": "https://example.com/photos/47.jpg"
    },
    {
        "id": "48",
        "gender": "Female",
        "name": "Stella Martinez",
        "contact": "+3333333333",
        "address": "876 Maple Ave, Village",
        "photoURL": "https://example.com/photos/48.jpg"
    },
    {
        "id": "49",
        "gender": "Male",
        "name": "Elijah Clark",
        "contact": "+4444444444",
        "address": "543 Oak St, Town",
        "photoURL": "https://example.com/photos/49.jpg"
    },
    {
        "id": "50",
        "gender": "Female",
        "name": "Lucy Anderson",
        "contact": "+5555555555",
        "address": "210 Pine St, City",
        "photoURL": "https://example.com/photos/50.jpg"
    }
]
